grpc_auth_service/__init__.py
grpc_auth_service/auth_service_pb2.py
grpc_auth_service/auth_service_pb2.pyi
grpc_auth_service/auth_service_pb2_grpc.py
grpc_auth_service/oauth_service_pb2.py
grpc_auth_service/oauth_service_pb2.pyi
grpc_auth_service/oauth_service_pb2_grpc.py
grpc_auth_service/py.typed
grpc_auth_service/role_service_pb2.py
grpc_auth_service/role_service_pb2.pyi
grpc_auth_service/role_service_pb2_grpc.py
grpc_auth_service/user_info_service_pb2.py
grpc_auth_service/user_info_service_pb2.pyi
grpc_auth_service/user_info_service_pb2_grpc.py
grpc_auth_service/user_service_pb2.py
grpc_auth_service/user_service_pb2.pyi
grpc_auth_service/user_service_pb2_grpc.py
grpc_auth_service/utils/__init__.py
grpc_auth_service/utils/constants.py
grpc_auth_service/utils/metadata.py
grpc_auth_service/utils/services.py
grpc_auth_service-0.0.40.dist-info/LICENSE
grpc_auth_service-0.0.40.dist-info/METADATA
grpc_auth_service-0.0.40.dist-info/WHEEL
grpc_auth_service-0.0.40.dist-info/top_level.txt
grpc_auth_service-0.0.40.dist-info/RECORD
