Metadata-Version: 2.1
Name: grpc_auth_service
Version: 0.0.40
Summary: A grpc autogenerated code for Auth microservice of online cinema
Author: Async Boat
Author-email: nestulej@gmail.com
Classifier: Programming Language :: Python :: 3
Classifier: License :: OSI Approved :: MIT License
Classifier: Operating System :: OS Independent
License-File: LICENSE
